[
    {
        "title": "Photography Jobs Opening in Novocom Ventures Private Limited at BangaloreLess",
        "company": "Novocom Ventures Private Limited",
        "location": "Bangalore",
        "description": "Apply to Photography Jobs in Novocom Ventures Private Li...",
        "experience": "0 Years",
        "salary": "Salary not disclosed",
        "link": "/jobs-in-bangalore/9999016065",
        "posted_on": "3 days ago"
    },
    {
        "title": "HR Recruiter Jobs Opening in Jnj technologies and services LLP at Vijayawada-Others, VijayawadaLess",
        "company": "Jnj technologies and services LLP",
        "location": "Vijayawada",
        "description": "Apply to HR Recruiter Jobs in Jnj technologies and servi...",
        "experience": "0 Years",
        "salary": "15000 - 25000 Monthly",
        "link": "/jobs-in-vijayawada/999902012",
        "posted_on": "3 days ago"
    },
    {
        "title": "HR Executive Jobs Opening in Styflowne Finance Services Private Limited at Anand Vihar, Chandni Chowk, Janpath, Mumbai, Noida, DelhiLess",
        "company": "Styflowne Finance Services Private Limited",
        "location": "Delhi, Mumbai, Noida",
        "description": "Apply to HR Executive Jobs in Styflowne Finance Services...",
        "experience": "0 Years",
        "salary": "8000 Monthly",
        "link": "/jobs-in-delhi/9999035026",
        "posted_on": "3 days ago"
    },
    {
        "title": "Recruiter Jobs Opening in Department of Women and Child Development at Central Delhi, Delhi-Others, Airport Gandhinagar Highway, Ahmedabad, Gurgaon, DelhiLess",
        "company": "Department of Women and Child Development",
        "location": "Delhi, Ahmedabad, Gurgaon",
        "description": "Apply to Recruiter Jobs in Department of Women and Child...",
        "experience": "0.6 to 1.5 Years",
        "salary": "15000 - 38000 Monthly",
        "link": "/jobs-in-delhi/9999035026",
        "posted_on": "3 days ago"
    },
    {
        "title": "HR Recruiter Jobs Opening in BELAKU JOBS at Rajajinagar, BangaloreLess",
        "company": "BELAKU JOBS",
        "location": "Bangalore",
        "description": "Apply to HR Recruiter Jobs in BELAKU JOBS, Bangalore fro...",
        "experience": "0 Years",
        "salary": "20000 - 30000 Monthly",
        "link": "/jobs-in-bangalore/9999016065",
        "posted_on": "3 days ago"
    },
    {
        "title": "Call Center Executive Jobs Opening in Votiko Solutions at Azara, Bannerghatta Road, Basaveshwara Nagar, Guwahati, Bangalore, KannurLess",
        "company": "Votiko Solutions",
        "location": "Guwahati, Bangalore, Kannur",
        "description": "Apply to Call Center Executive Jobs in Votiko Solutions,...",
        "experience": "0 Years",
        "salary": "20000 - 70000 Monthly",
        "link": "/jobs-in-guwahati/999904016",
        "posted_on": "3 days ago"
    },
    {
        "title": "Call Center Executive Jobs Opening in Votiko Solutions at Azadpur, Connaught Place, Okhla, Ahmedabad, Bangalore, DelhiLess",
        "company": "Votiko Solutions",
        "location": "Delhi, Ahmedabad, Bangalore",
        "description": "Apply to Call Center Executive Jobs in Votiko Solutions,...",
        "experience": "0 Years",
        "salary": "20000 - 70000 Monthly",
        "link": "/jobs-in-delhi/9999035026",
        "posted_on": "4 days ago"
    },
    {
        "title": "Financial Advisor Jobs Opening in LEADING LIFE INSURANCE at Lucknow, Lakhimpur KheriLess",
        "company": "LEADING LIFE INSURANCE",
        "location": "Lucknow, Lakhimpur Kheri",
        "description": "Apply to Financial Advisor Jobs in LEADING LIFE INSURANC...",
        "experience": "0 Years",
        "salary": "35000 - 100000 Monthly",
        "link": "/jobs-in-lucknow/99990320148",
        "posted_on": "4 days ago"
    },
    {
        "title": "Business Analyst Jobs Opening in SDS Softpro at Noida-Others, NoidaLess",
        "company": "SDS Softpro",
        "location": "Noida",
        "description": "Apply to Business Analyst Jobs in SDS Softpro, Noida fro...",
        "experience": "0 Years",
        "salary": "10000 - 20000 Monthly",
        "link": "/jobs-in-noida/99990320152",
        "posted_on": "5 days ago"
    },
    {
        "title": "Data Entry Operator Jobs Opening in Inet.solution at Avinashi Road, Ganapathy, Peelamedu, CoimbatoreLess",
        "company": "Inet.solution",
        "location": "Coimbatore",
        "description": "Apply to Data Entry Operator Jobs in Inet.solution, Coim...",
        "experience": "0 Years",
        "salary": "7000 - 18000 Monthly",
        "link": "/jobs-in-coimbatore/99990300126",
        "posted_on": "5 days ago"
    },
    {
        "title": "Telecaller Jobs Opening in GEI at Adarsh Nagar, Bindayaka, C Scheme, JaipurLess",
        "company": "GEI",
        "location": "Jaipur",
        "description": "Apply to Telecaller Jobs in GEI, Jaipur from fresher. Fi...",
        "experience": "0 Years",
        "salary": "5000 - 10000 Monthly",
        "link": "/jobs-in-jaipur/99990280119",
        "posted_on": "5 days ago"
    },
    {
        "title": "Software Engineer Intern Jobs Opening in Tecell India Private Limited at Rajarajeshwari Nagar, BangaloreLess",
        "company": "Tecell India Private Limited",
        "location": "Bangalore",
        "description": "Apply to Software Engineer Intern Jobs in Tecell India P...",
        "experience": "0 Years",
        "salary": "5000 Monthly",
        "link": "/jobs-in-bangalore/9999016065",
        "posted_on": "6 days ago"
    },
    {
        "title": "Telecaller Jobs Opening in Solviffy at Dum Dum, Hatibagan, Salt Lake, KolkataLess",
        "company": "Solviffy",
        "location": "Kolkata",
        "description": "Apply to Telecaller Jobs in Solviffy, Kolkata from fresh...",
        "experience": "0 Years",
        "salary": "20000 - 30000 Monthly",
        "link": "/jobs-in-kolkata/99990340160",
        "posted_on": "6 days ago"
    },
    {
        "title": "Freelance/ Part-Time - Insurance Advisor Jobs Opening in Tata AIA at Gachibowli, Bangalore, Pune, HyderabadLess",
        "company": "Tata AIA",
        "location": "Hyderabad, Bangalore, Pune",
        "description": "Apply to Freelance/ Part-Time - Insurance Advisor Jobs i...",
        "experience": "0 Years",
        "salary": "50000 - 300000 Monthly",
        "link": "/jobs-in-hyderabad/999903705",
        "posted_on": "6 days ago"
    },
    {
        "title": "Website Developer Jobs Opening in Ideal Career Zone at Shyam Bazar, KolkataLess",
        "company": "Ideal Career Zone",
        "location": "Kolkata",
        "description": "Apply to Website Developer Jobs in Ideal Career Zone, Ko...",
        "experience": "0 Years",
        "salary": "10000 - 30000 Monthly",
        "link": "/jobs-in-kolkata/99990340160",
        "posted_on": "6 days ago"
    },
    {
        "title": "Billing Executive Jobs Opening in Grand godwin hotel at DelhiLess",
        "company": "Grand godwin hotel",
        "location": "Delhi",
        "description": "Apply to Billing Executive Jobs in Grand godwin hotel, D...",
        "experience": "0 Years",
        "salary": "Salary not disclosed",
        "link": "/jobs-in-delhi/9999035026",
        "posted_on": "6 days ago"
    },
    {
        "title": "SEO Executive Jobs Opening in FUNFULTRIP at Laxmi Nagar, Ghaziabad, Noida, DelhiLess",
        "company": "FUNFULTRIP",
        "location": "Delhi, Ghaziabad, Noida",
        "description": "Apply to SEO Executive Jobs in FUNFULTRIP, Ghaziabad, No...",
        "experience": "0 Years",
        "salary": "10000 - 15000 Monthly",
        "link": "/jobs-in-delhi/9999035026",
        "posted_on": "7 days ago"
    },
    {
        "title": "HR Executive Jobs Opening in Skyflowne finance services pvt ltd at Noida-Others, NoidaLess",
        "company": "Skyflowne finance services pvt ltd",
        "location": "Noida",
        "description": "Apply to HR Executive Jobs in Skyflowne finance services...",
        "experience": "0 Years",
        "salary": "Salary not disclosed",
        "link": "/jobs-in-noida/99990320152",
        "posted_on": "7 days ago"
    },
    {
        "title": "Software Trainee Jobs Opening in KIPSMA PVT. LTD. at Noida-Others, NoidaLess",
        "company": "KIPSMA PVT. LTD.",
        "location": "Noida",
        "description": "Apply to Software Trainee Jobs in KIPSMA PVT. LTD., Noid...",
        "experience": "0 Years",
        "salary": "Salary not disclosed",
        "link": "/jobs-in-noida/99990320152",
        "posted_on": "7 days ago"
    },
    {
        "title": "Call Center Executive Jobs Opening in Votiko Solutions at Bavdhan, Bund Garden Road, Deccan Gymkhana, PuneLess",
        "company": "Votiko Solutions",
        "location": "Pune",
        "description": "Apply to Call Center Executive Jobs in Votiko Solutions,...",
        "experience": "0 Years",
        "salary": "20000 - 70000 Monthly",
        "link": "/jobs-in-pune/9999020098",
        "posted_on": "7 days ago"
    },
    {
        "title": "Business Executive Jobs Opening in Jeevan Health Care at Kolkata-Others, KolkataLess",
        "company": "Jeevan Health Care",
        "location": "Kolkata",
        "description": "Apply to Business Executive Jobs in Jeevan Health Care, ...",
        "experience": "0 Years",
        "salary": "Salary not disclosed",
        "link": "/jobs-in-kolkata/99990340160",
        "posted_on": "8 days ago"
    },
    {
        "title": "Content Intern Jobs Opening in Born In Flight at Basaveshwara Nagar, BangaloreLess",
        "company": "Born In Flight",
        "location": "Bangalore",
        "description": "Apply to Content Intern Jobs in Born In Flight, Bangalor...",
        "experience": "0 Years",
        "salary": "3000 Monthly",
        "link": "/jobs-in-bangalore/9999016065",
        "posted_on": "8 days ago"
    },
    {
        "title": "Graphic Designer Jobs Opening in ADDHURI EVENTS at Brookefields, BangaloreLess",
        "company": "ADDHURI EVENTS",
        "location": "Bangalore",
        "description": "Apply to Graphic Designer Jobs in ADDHURI EVENTS, Bangal...",
        "experience": "0 Years",
        "salary": "15000 - 25000 Monthly",
        "link": "/jobs-in-bangalore/9999016065",
        "posted_on": "8 days ago"
    },
    {
        "title": "Call Center Executives Jobs Opening in Votiko Solutions at Ameerpet, Sector 15, Noida, Salt Lake, Noida, Kolkata, HyderabadLess",
        "company": "Votiko Solutions",
        "location": "Hyderabad, Noida, Kolkata",
        "description": "Apply to Call Center Executives Jobs in Votiko Solutions...",
        "experience": "0 Years",
        "salary": "20000 - 70000 Monthly",
        "link": "/jobs-in-hyderabad/999903705",
        "posted_on": "8 days ago"
    },
    {
        "title": "Operations Officer Jobs Opening in J Consultants at Saibaba Colony, CoimbatoreLess",
        "company": "J Consultants",
        "location": "Coimbatore",
        "description": "Apply to Operations Officer Jobs in J Consultants, Coimb...",
        "experience": "0 Years",
        "salary": "8000 - 12000 Monthly",
        "link": "/jobs-in-coimbatore/99990300126",
        "posted_on": "8 days ago"
    },
    {
        "title": "Telecaller Jobs Opening in WIRE MONSTER at ChandigarhLess",
        "company": "WIRE MONSTER",
        "location": "Chandigarh",
        "description": "Apply to Telecaller Jobs in WIRE MONSTER, Chandigarh fro...",
        "experience": "0 Years",
        "salary": "7000 - 20000 Monthly",
        "link": "/jobs-in-chandigarh/999906",
        "posted_on": "8 days ago"
    },
    {
        "title": "HR Internship Jobs Opening in Addhuri Events OPC Private Limited at Amraiwadi, Borivali East, Ahmedabad, Bhuj, MumbaiLess",
        "company": "Addhuri Events OPC Private Limited",
        "location": "Ahmedabad, Bhuj, Mumbai",
        "description": "Apply to HR Internship Jobs in Addhuri Events OPC Privat...",
        "experience": "0 Years",
        "salary": "25000 - 45000 Monthly",
        "link": "/jobs-in-ahmedabad/9999011030",
        "posted_on": "8 days ago"
    },
    {
        "title": "HR Recruiter Jobs Opening in Addhuri Events OPC Private Limited at Ambavadi, Borivali West, Ahmedabad, Bhuj, MumbaiLess",
        "company": "Addhuri Events OPC Private Limited",
        "location": "Ahmedabad, Bhuj, Mumbai",
        "description": "Apply to HR Recruiter Jobs in Addhuri Events OPC Private...",
        "experience": "0 Years",
        "salary": "Salary not disclosed",
        "link": "/jobs-in-ahmedabad/9999011030",
        "posted_on": "8 days ago"
    },
    {
        "title": "Call Center Executive Jobs Opening in Votiko Solutions at Railway Station Road, Shamshabad, Alaknanda, Ahmedabad, Delhi, HyderabadLess",
        "company": "Votiko Solutions",
        "location": "Hyderabad, Delhi, Ahmedabad",
        "description": "Apply to Call Center Executive Jobs in Votiko Solutions,...",
        "experience": "0 Years",
        "salary": "20000 - 70000 Monthly",
        "link": "/jobs-in-hyderabad/999903705",
        "posted_on": "9 days ago"
    },
    {
        "title": "Insurance Advisor Jobs Opening in FUTURE ASSETS at Aminijikarai, Choolaimedu, K.K. Nagar, ChennaiLess",
        "company": "FUTURE ASSETS",
        "location": "Chennai",
        "description": "Apply to Insurance Advisor Jobs in FUTURE ASSETS, Chenna...",
        "experience": "0 Years",
        "salary": "25000 - 100000 Monthly",
        "link": "/jobs-in-chennai/99990300125",
        "posted_on": "10 days ago"
    },
    {
        "title": "Data Entry Operator Jobs Opening in Trading Euphoria at Yelahanka, BangaloreLess",
        "company": "Trading Euphoria",
        "location": "Bangalore",
        "description": "Apply to Data Entry Operator Jobs in Trading Euphoria, B...",
        "experience": "0 Years",
        "salary": "5000 - 5500 Monthly",
        "link": "/jobs-in-bangalore/9999016065",
        "posted_on": "10 days ago"
    },
    {
        "title": "Remote Work From Home Jobs Opening in Digitalize at Patna, Bhubaneswar, DehradunLess",
        "company": "Digitalize",
        "location": "Patna, Bhubaneswar, Dehradun",
        "description": "Apply to Remote Work From Home Jobs in Digitalize, Patna...",
        "experience": "0 Years",
        "salary": "10000 - 15000 Monthly",
        "link": "/jobs-in-patna/999905019",
        "posted_on": "10 days ago"
    },
    {
        "title": "Branding And Marketing Intern Jobs Opening in APPNEURAL Pvt. Ltd. at UdaipurLess",
        "company": "APPNEURAL Pvt. Ltd.",
        "location": "Udaipur",
        "description": "Apply to Branding And Marketing Intern Jobs in APPNEURAL...",
        "experience": "0 Years",
        "salary": "Salary not disclosed",
        "link": "/jobs-in-udaipur/99990280123",
        "posted_on": "10 days ago"
    },
    {
        "title": "HR Intern Jobs Opening in FeminineJobs at Bannerghatta Road, BangaloreLess",
        "company": "FeminineJobs",
        "location": "Bangalore",
        "description": "Apply to HR Intern Jobs in FeminineJobs, Bangalore from ...",
        "experience": "0 Years",
        "salary": "Salary not disclosed",
        "link": "/jobs-in-bangalore/9999016065",
        "posted_on": "11 days ago"
    },
    {
        "title": "Junior Software Developer Jobs Opening in Thinklabs LLC at Gachibowli, Jeedimetla, Kacheguda, Ahmedabad, Bangalore, HyderabadLess",
        "company": "Thinklabs LLC",
        "location": "Hyderabad, Ahmedabad, Bangalore",
        "description": "Apply to Junior Software Developer Jobs in Thinklabs LLC...",
        "experience": "0 Years",
        "salary": "20000 - 25000 Monthly",
        "link": "/jobs-in-hyderabad/999903705",
        "posted_on": "11 days ago"
    },
    {
        "title": "We Are Providing Online Data Entry Work At Home Based Work Jobs Opening in Spancore technology at 100 Feet Road, Ganapathy, Peelamedu, CoimbatoreLess",
        "company": "Spancore technology",
        "location": "Coimbatore",
        "description": "Apply to We Are Providing Online Data Entry Work At Home...",
        "experience": "0 Years",
        "salary": "4500 - 6500 Monthly",
        "link": "/jobs-in-coimbatore/99990300126",
        "posted_on": "13 days ago"
    },
    {
        "title": "Data Entry Specialist Jobs Opening in Ayatrio at Camac Street Area, KolkataLess",
        "company": "Ayatrio",
        "location": "Kolkata",
        "description": "Apply to Data Entry Specialist Jobs in Ayatrio, Kolkata ...",
        "experience": "0 Years",
        "salary": "Salary not disclosed",
        "link": "/jobs-in-kolkata/99990340160",
        "posted_on": "14 days ago"
    },
    {
        "title": "Telecaller Jobs Opening in G. I group at Anand Vihar, Ashok Vihar, Bhikaji Cama Place, Ahmedabad, Kolkata, DelhiLess",
        "company": "G. I group",
        "location": "Delhi, Ahmedabad, Kolkata",
        "description": "Apply to Telecaller Jobs in G. I group, Ahmedabad, Kolka...",
        "experience": "0 Years",
        "salary": "15000 - 25000 Monthly",
        "link": "/jobs-in-delhi/9999035026",
        "posted_on": "15 days ago"
    },
    {
        "title": "Data Entry Computer Operator Jobs Opening in Balaji Trading at MuzaffarpurLess",
        "company": "Balaji Trading",
        "location": "Muzaffarpur",
        "description": "Apply to Data Entry Computer Operator Jobs in Balaji Tra...",
        "experience": "0 Years",
        "salary": "5000 - 15000 Monthly",
        "link": "/jobs-in-muzaffarpur/9999050166",
        "posted_on": "16 days ago"
    },
    {
        "title": "Blog Content Writer Jobs Opening in Hookedme at Shibpur, Kolkata, HowrahLess",
        "company": "Hookedme",
        "location": "Kolkata, Howrah",
        "description": "Apply to Blog Content Writer Jobs in Hookedme, Kolkata, ...",
        "experience": "0 Years",
        "salary": "Salary not disclosed",
        "link": "/jobs-in-kolkata/99990340160",
        "posted_on": "16 days ago"
    },
    {
        "title": "BPO/Telecaller Jobs Opening in Forever livingMultinational company at Begumpet, HyderabadLess",
        "company": "Forever livingMultinational company",
        "location": "Hyderabad",
        "description": "Apply to BPO/Telecaller Jobs in Forever livingMultinatio...",
        "experience": "0 Years",
        "salary": "25000 - 35000 Monthly",
        "link": "/jobs-in-hyderabad/999903705",
        "posted_on": "17 days ago"
    },
    {
        "title": "HR Internship Jobs Opening in Addhuri Events Pvt Ltd at Delhi-Others, DelhiLess",
        "company": "Addhuri Events Pvt Ltd",
        "location": "Delhi",
        "description": "Apply to HR Internship Jobs in Addhuri Events Pvt Ltd, D...",
        "experience": "0 Years",
        "salary": "15000 - 45000 Monthly",
        "link": "/jobs-in-delhi/9999035026",
        "posted_on": "17 days ago"
    },
    {
        "title": "HR Internship Jobs Opening in Addhuri events at Bangalore-Others, BangaloreLess",
        "company": "Addhuri events",
        "location": "Bangalore",
        "description": "Apply to HR Internship Jobs in Addhuri events, Bangalore...",
        "experience": "0 Years",
        "salary": "15000 - 45000 Monthly",
        "link": "/jobs-in-bangalore/9999016065",
        "posted_on": "17 days ago"
    },
    {
        "title": "Typing Work From Home Jobs Opening in CHRISTTECH at Dhanbad, Jamshedpur, RanchiLess",
        "company": "CHRISTTECH",
        "location": "Dhanbad, Jamshedpur, Ranchi",
        "description": "Apply to Typing Work From Home Jobs in CHRISTTECH, Dhanb...",
        "experience": "0 Years",
        "salary": "7500 - 12000 Monthly",
        "link": "/jobs-in-dhanbad/9999015062",
        "posted_on": "17 days ago"
    },
    {
        "title": "Dot Net Developer Jobs Opening in Percept infosystem consultant at Gandhi Nagar, Jaripatka, Laxmi Nagar, NagpurLess",
        "company": "Percept infosystem consultant",
        "location": "Nagpur",
        "description": "Apply to Dot Net Developer Jobs in Percept infosystem co...",
        "experience": "0 Years",
        "salary": "7000 - 7001 Monthly",
        "link": "/jobs-in-nagpur/9999020095",
        "posted_on": "18 days ago"
    },
    {
        "title": "Telecaller Jobs Opening in Percept infosystem consultant at Jaripatka, Laxmi Nagar, Rana Pratap Nagar, NagpurLess",
        "company": "Percept infosystem consultant",
        "location": "Nagpur",
        "description": "Apply to Telecaller Jobs in Percept infosystem consultan...",
        "experience": "0 Years",
        "salary": "7000 - 15000 Monthly",
        "link": "/jobs-in-nagpur/9999020095",
        "posted_on": "18 days ago"
    },
    {
        "title": "Administration Executive Jobs Opening in Talentgram agency llp at Charni Road, MumbaiLess",
        "company": "Talentgram agency llp",
        "location": "Mumbai",
        "description": "Apply to Administration Executive Jobs in Talentgram age...",
        "experience": "0 Years",
        "salary": "15000 - 25000 Monthly",
        "link": "/jobs-in-mumbai/9999020093",
        "posted_on": "18 days ago"
    },
    {
        "title": "HR Internship Jobs Opening in Prointerns at HSR, BangaloreLess",
        "company": "Prointerns",
        "location": "Bangalore",
        "description": "Apply to HR Internship Jobs in Prointerns, Bangalore fro...",
        "experience": "0 Years",
        "salary": "45000 - 60000 Monthly",
        "link": "/jobs-in-bangalore/9999016065",
        "posted_on": "18 days ago"
    },
    {
        "title": "NodeJs Trainer Jobs Opening in Mukund Programming Tutorials at Delhi-Others, Gurgaon City Centre, Gurgaon-Others, Gurgaon, Noida, DelhiLess",
        "company": "Mukund Programming Tutorials",
        "location": "Delhi, Gurgaon, Noida",
        "description": "Apply to NodeJs Trainer Jobs in Mukund Programming Tutor...",
        "experience": "0 Years",
        "salary": "5000 - 8000 Monthly",
        "link": "/jobs-in-delhi/9999035026",
        "posted_on": "18 days ago"
    },
    {
        "title": "Back Office/Data Entry Jobs Opening in Our Company at C G Road, AhmedabadLess",
        "company": "Our Company",
        "location": "Ahmedabad",
        "description": "Apply to Back Office/Data Entry Jobs in Our Company, Ahm...",
        "experience": "0 Years",
        "salary": "7000 - 8000 Monthly",
        "link": "/jobs-in-ahmedabad/9999011030",
        "posted_on": "19 days ago"
    },
    {
        "title": "Recruitment Executive Jobs Opening in NAVM HR Services LLP at Ashok Vihar, DelhiLess",
        "company": "NAVM HR Services LLP",
        "location": "Delhi",
        "description": "Apply to Recruitment Executive Jobs in NAVM HR Services ...",
        "experience": "0 Years",
        "salary": "10000 - 15000 Monthly",
        "link": "/jobs-in-delhi/9999035026",
        "posted_on": "20 days ago"
    },
    {
        "title": "Junior Android Developer Jobs Opening in Smartappgenerator at Ameerpet, Kukatpally, Madhapur, HyderabadLess",
        "company": "Smartappgenerator",
        "location": "Hyderabad",
        "description": "Apply to Junior Android Developer Jobs in Smartappgenera...",
        "experience": "0 to 2 Years",
        "salary": "10000 - 20000 Monthly",
        "link": "/jobs-in-hyderabad/999903705",
        "posted_on": "20 days ago"
    }
]